ccut/__init__.py
ccut/data/labels_extension.json
ccut/data/quantity_dimension.json
ccut/data/unit.owl
ccut/data/uri_prios.json
ccut/data/user_defined.json
ccut/main/__init__.py
ccut/main/canonical_compound_unit.py
ccut/main/canonical_compound_unit_transformation.py
ccut/main/canonical_simple_unit.py
ccut/main/ccut_main.py
ccut/main/compound_unit.py
ccut/main/config.py
ccut/main/currency_symbols.py
ccut/main/dimension.py
ccut/main/dimension_map.py
ccut/main/qudt_unit.py
ccut/main/rdf_parser.py
ccut/main/si_prefix.py
ccut/main/symbol_map.py
ccut/main/unit.py
ccut/main/unit_match.py
ccut/main/unit_parser.py
ccut/main/unit_visitor.py
ccut/tests/__init__.py
ccut/tests/canonical_compound_unit_trans_test.py
ccut/tests/canonical_simple_unit_test.py
ccut/tests/ccu_test.py
ccut/tests/dimension_test.py
ccut/tests/si_prefix_test.py
ccut/tests/symbol_map_test.py
ccut/tests/unit_match_test.py
ccut-1.0.0.dist-info/LICENSE
ccut-1.0.0.dist-info/METADATA
ccut-1.0.0.dist-info/WHEEL
ccut-1.0.0.dist-info/top_level.txt
ccut-1.0.0.dist-info/RECORD
