Metadata-Version: 2.1
Name: ccut
Version: 1.0.0
Summary: A package for identifying, parsing and transforming units of measure
Home-page: https://github.com/basels/ccut/
Author: Basel Shbita
Author-email: basel921@gmail.com
License: UNKNOWN
Platform: UNKNOWN
Classifier: Programming Language :: Python :: 3
Classifier: License :: OSI Approved :: MIT License
Classifier: Operating System :: OS Independent
Requires-Python: >=3.6
Requires-Dist: arpeggio (>=1.9.2)
Requires-Dist: rdflib (>=4.2.2)
